zededa_edgeai_sdk/__init__.py
zededa_edgeai_sdk/cli.py
zededa_edgeai_sdk/client.py
zededa_edgeai_sdk/config.py
zededa_edgeai_sdk/environment.py
zededa_edgeai_sdk/exceptions.py
zededa_edgeai_sdk/zededa_edgeai_sdk.py
zededa_edgeai_sdk/commands/__init__.py
zededa_edgeai_sdk/commands/benchmarks.py
zededa_edgeai_sdk/commands/catalogs.py
zededa_edgeai_sdk/commands/external_providers.py
zededa_edgeai_sdk/commands/import_jobs.py
zededa_edgeai_sdk/commands/login.py
zededa_edgeai_sdk/commands/logout.py
zededa_edgeai_sdk/commands/set_catalog_context.py
zededa_edgeai_sdk/services/__init__.py
zededa_edgeai_sdk/services/auth.py
zededa_edgeai_sdk/services/benchmarks.py
zededa_edgeai_sdk/services/catalogs.py
zededa_edgeai_sdk/services/external_providers.py
zededa_edgeai_sdk/services/http.py
zededa_edgeai_sdk/services/import_jobs.py
zededa_edgeai_sdk/services/storage.py
zededa_edgeai_sdk/utils/__init__.py
zededa_edgeai_sdk/utils/formatters.py
zededa_edgeai_sdk-2.0.0.dist-info/licenses/LICENSE
zededa_edgeai_sdk-2.0.0.dist-info/METADATA
zededa_edgeai_sdk-2.0.0.dist-info/WHEEL
zededa_edgeai_sdk-2.0.0.dist-info/entry_points.txt
zededa_edgeai_sdk-2.0.0.dist-info/top_level.txt
zededa_edgeai_sdk-2.0.0.dist-info/RECORD
