Metadata-Version: 2.4
Name: zededa-edgeai-sdk
Version: 2.0.0
Summary: Zededa EdgeAI SDK - CLI and Python library for authentication and MLflow integration
Author-email: Zededa <support@zededa.com>
License: Apache-2.0
Project-URL: Homepage, https://github.com/zededa/edgeai
Project-URL: Issues, https://github.com/zededa/edgeai/issues
Classifier: Development Status :: 4 - Beta
Classifier: Intended Audience :: Developers
Classifier: License :: OSI Approved :: Apache Software License
Classifier: Operating System :: OS Independent
Classifier: Programming Language :: Python :: 3
Classifier: Programming Language :: Python :: 3.8
Classifier: Programming Language :: Python :: 3.9
Classifier: Programming Language :: Python :: 3.10
Classifier: Programming Language :: Python :: 3.11
Requires-Python: >=3.8
License-File: LICENSE
Requires-Dist: requests>=2.31.0
Dynamic: license-file
